FlightBEND/__init__.py
FlightBEND/beam_section.py
FlightBEND/fem_BCs.py
FlightBEND/fem_geometry.py
flightbend-1.0.2.dist-info/licenses/LICENSE
flightbend-1.0.2.dist-info/METADATA
flightbend-1.0.2.dist-info/WHEEL
flightbend-1.0.2.dist-info/entry_points.txt
flightbend-1.0.2.dist-info/top_level.txt
flightbend-1.0.2.dist-info/RECORD
