Metadata-Version: 2.4
Name: FlightBEND
Version: 1.0.2
Summary: A Python package for flexible body dynamics simulation of airframes
Author-email: Pedro Pires <pfmppedro@gmail.com>, Tiago Buriol <tiago.buriol@ufsm.br>
License: MIT
Requires-Python: >=3.11
License-File: LICENSE
Requires-Dist: numpy>=1.24.3
Requires-Dist: matplotlib>=3.7.2
Requires-Dist: scipy>=1.11.1
Requires-Dist: nptyping>=2.5.0
Dynamic: license-file
